scarlet_shark_client/__init__.py
scarlet_shark_client/client.py
scarlet_shark_client/clients/__init__.py
scarlet_shark_client/clients/abstract.py
scarlet_shark_client/clients/v04_client.py
scarlet_shark_client-1.0.5.dist-info/LICENSE.txt
scarlet_shark_client-1.0.5.dist-info/METADATA
scarlet_shark_client-1.0.5.dist-info/WHEEL
scarlet_shark_client-1.0.5.dist-info/top_level.txt
scarlet_shark_client-1.0.5.dist-info/RECORD
